odoo/addons/facto/__init__.py
odoo/addons/facto/__manifest__.py
odoo/addons/facto/models/__init__.py
odoo/addons/facto/models/account_invoice.py
odoo12_addon_facto-12.0.0.0.3.dist-info/METADATA
odoo12_addon_facto-12.0.0.0.3.dist-info/WHEEL
odoo12_addon_facto-12.0.0.0.3.dist-info/top_level.txt
odoo12_addon_facto-12.0.0.0.3.dist-info/RECORD
